{
  "$schema": "https://developer.microsoft.com/json-schemas/fabric/item/report/definition/visualContainer/2.1.0/schema.json",
  "name": "195d58f10adae48965d7",
  "position": {
    "x": 14.965062643669413,
    "y": 266.87695047877122,
    "z": 11000,
    "height": 52.377719252842944,
    "width": 300.54834142702737,
    "tabOrder": 10000
  },
  "visual": {
    "visualType": "kpi",
    "query": {
      "queryState": {
        "Goal": {
          "projections": [
            {
              "field": {
                "Aggregation": {
                  "Expression": {
                    "Column": {
                      "Expression": {
                        "SourceRef": {
                          "Entity": "BI_SFDC_BOOKINGS_ANNUALIZED_ACV_YOY"
                        }
                      },
                      "Property": "Target"
                    }
                  },
                  "Function": 0
                }
              },
              "queryRef": "Sum(BI_SFDC_BOOKINGS_ANNUALIZED_ACV_YOY.Target)",
              "nativeQueryRef": "Sum of Target"
            }
          ]
        },
        "Indicator": {
          "projections": [
            {
              "field": {
                "Aggregation": {
                  "Expression": {
                    "Column": {
                      "Expression": {
                        "SourceRef": {
                          "Entity": "BI_SFDC_BOOKINGS_ANNUALIZED_ACV_YOY"
                        }
                      },
                      "Property": "Forecast"
                    }
                  },
                  "Function": 0
                }
              },
              "queryRef": "Sum(BI_SFDC_BOOKINGS_ANNUALIZED_ACV_YOY.Forecast)",
              "nativeQueryRef": "Sum of Forecast"
            }
          ]
        },
        "TrendLine": {
          "projections": [
            {
              "field": {
                "Column": {
                  "Expression": {
                    "SourceRef": {
                      "Entity": "BI_SFDC_BOOKINGS_ANNUALIZED_ACV_YOY"
                    }
                  },
                  "Property": "Target"
                }
              },
              "queryRef": "BI_SFDC_BOOKINGS_ANNUALIZED_ACV_YOY.Target",
              "nativeQueryRef": "Target"
            }
          ]
        }
      }
    },
    "objects": {
      "lastDate": [
        {
          "properties": {
            "show": {
              "expr": {
                "Literal": {
                  "Value": "false"
                }
              }
            }
          }
        }
      ],
      "goals": [
        {
          "properties": {
            "showGoal": {
              "expr": {
                "Literal": {
                  "Value": "true"
                }
              }
            },
            "goalText": {
              "expr": {
                "Literal": {
                  "Value": "'Target'"
                }
              }
            },
            "fontSize": {
              "expr": {
                "Literal": {
                  "Value": "9D"
                }
              }
            }
          }
        }
      ],
      "indicator": [
        {
          "properties": {
            "fontSize": {
              "expr": {
                "Literal": {
                  "Value": "23D"
                }
              }
            },
            "showIcon": {
              "expr": {
                "Literal": {
                  "Value": "false"
                }
              }
            }
          }
        }
      ],
      "status": [
        {
          "properties": {
            "badColor": {
              "solid": {
                "color": {
                  "expr": {
                    "Literal": {
                      "Value": "'#008F88'"
                    }
                  }
                }
              }
            },
            "neutralColor": {
              "solid": {
                "color": {
                  "expr": {
                    "Literal": {
                      "Value": "'#008F88'"
                    }
                  }
                }
              }
            },
            "goodColor": {
              "solid": {
                "color": {
                  "expr": {
                    "Literal": {
                      "Value": "'#008F88'"
                    }
                  }
                }
              }
            }
          }
        }
      ]
    },
    "visualContainerObjects": {
      "title": [
        {
          "properties": {
            "text": {
              "expr": {
                "Literal": {
                  "Value": "'Forecast Vs Target'"
                }
              }
            },
            "fontSize": {
              "expr": {
                "Literal": {
                  "Value": "9D"
                }
              }
            }
          }
        }
      ],
      "background": [
        {
          "properties": {
            "show": {
              "expr": {
                "Literal": {
                  "Value": "false"
                }
              }
            }
          }
        }
      ]
    },
    "drillFilterOtherVisuals": true
  },
  "filterConfig": {
    "filters": [
      {
        "name": "12be8c94b5d242862da7",
        "field": {
          "Column": {
            "Expression": {
              "SourceRef": {
                "Entity": "BI_SFDC_BOOKINGS_ANNUALIZED_ACV_YOY"
              }
            },
            "Property": "Product Line"
          }
        },
        "type": "Categorical",
        "howCreated": "User",
        "objects": {
          "general": [
            {
              "properties": {}
            }
          ]
        }
      }
    ]
  }
}